axuy/__init__.py
axuy/__main__.py
axuy/control.py
axuy/display.py
axuy/misc.py
axuy/peer.py
axuy/pico.py
axuy/settings.ini
axuy/assets/__init__.py
axuy/assets/chickenV2.mtl
axuy/assets/chickenV2.obj
axuy/assets/icon.png
axuy/assets/map.npy
axuy/assets/rock01.obj
axuy/assets/wall-color.png
axuy/assets/wall-norm.png
axuy/shaders/__init__.py
axuy/shaders/comb.frag
axuy/shaders/gauss.frag
axuy/shaders/gaussh.vert
axuy/shaders/gaussv.vert
axuy/shaders/map.frag
axuy/shaders/map.vert
axuy/shaders/pico.frag
axuy/shaders/pico.geom
axuy/shaders/pico.vert
axuy/shaders/sat.frag
axuy/shaders/tex.vert
axuy-0.0.12.dist-info/entry_points.txt
axuy-0.0.12.dist-info/LICENSE
axuy-0.0.12.dist-info/WHEEL
axuy-0.0.12.dist-info/METADATA
axuy-0.0.12.dist-info/RECORD
