Metadata-Version: 2.1
Name: axuy
Version: 0.0.12
Summary: Axuy is a minimalist peer-to-peer first-person shooter.
Home-page: https://sr.ht/~cnx/axuy
License: AGPLv3+
Keywords: fps,p2p,opengl,glfw
Author: Nguyễn Gia Phong
Author-email: mcsinyx@disroot.org
Requires-Python: >=3.7
Classifier: Development Status :: 3 - Alpha
Classifier: Environment :: MacOS X
Classifier: Environment :: Win32 (MS Windows)
Classifier: Environment :: X11 Applications
Classifier: Intended Audience :: End Users/Desktop
Classifier: License :: OSI Approved :: GNU Affero General Public License v3 or later (AGPLv3+)
Classifier: Natural Language :: English
Classifier: Operating System :: OS Independent
Classifier: Programming Language :: Python :: 3.7
Classifier: Programming Language :: Python :: 3.8
Classifier: Programming Language :: Python :: 3.9
Classifier: Programming Language :: Python :: 3 :: Only
Classifier: Topic :: Games/Entertainment :: First Person Shooters
Requires-Dist: appdirs
Requires-Dist: glfw>=1.8
Requires-Dist: moderngl
Requires-Dist: numpy
Requires-Dist: Pillow
Requires-Dist: pyrr
Requires-Dist: pywavefront
